quantalytics/__init__.py
quantalytics/analytics/__init__.py
quantalytics/analytics/benchmarks.py
quantalytics/analytics/metrics.py
quantalytics/analytics/stats.py
quantalytics/charts/__init__.py
quantalytics/charts/timeseries.py
quantalytics/reports/__init__.py
quantalytics/reports/metric_registry.py
quantalytics/reports/metrics.py
quantalytics/reports/tearsheet.py
quantalytics/reports/templates/tearsheet.html
quantalytics/utils/__init__.py
quantalytics/utils/timeseries.py
quantalytics-0.1.24.dist-info/licenses/LICENSE
quantalytics-0.1.24.dist-info/METADATA
quantalytics-0.1.24.dist-info/WHEEL
quantalytics-0.1.24.dist-info/top_level.txt
quantalytics-0.1.24.dist-info/RECORD
