Metadata-Version: 2.4
Name: quantalytics
Version: 0.1.24
Summary: Modern quantitative analysis library for portfolio analytics, charts, and reports
Author: Tyler Patterson
License: MIT License
Project-URL: Homepage, https://github.com/pattertj/quantalytics
Project-URL: Issues, https://github.com/pattertj/quantalytics/issues
Keywords: analytics,charts,finance,metrics,quantitative,reporting,statistics,visualization
Classifier: Development Status :: 3 - Alpha
Classifier: Intended Audience :: Financial and Insurance Industry
Classifier: License :: OSI Approved :: MIT License
Classifier: Programming Language :: Python
Classifier: Programming Language :: Python :: 3 :: Only
Classifier: Programming Language :: Python :: 3.9
Classifier: Programming Language :: Python :: 3.10
Classifier: Programming Language :: Python :: 3.11
Classifier: Programming Language :: Python :: 3.12
Classifier: Programming Language :: Python :: 3.13
Classifier: Programming Language :: Python :: 3.14
Classifier: Topic :: Office/Business :: Financial :: Investment
Classifier: Topic :: Scientific/Engineering :: Information Analysis
Requires-Python: >=3.9
License-File: LICENSE
Requires-Dist: jinja2>=3.1
Requires-Dist: narwhals>=2.10.2
Requires-Dist: numpy>=1.23
Requires-Dist: pandas>=1.5
Requires-Dist: plotly>=5.15
Requires-Dist: scipy>=1.9
Dynamic: license-file
